public class com/roscopeco/jasm/DoubleMathTests implements com/roscopeco/jasm/model/DoubleMathTests {
    public testD2f(D)F {
        dload 1
        d2f
        freturn
    }

    public testD2i(D)I {
        dload 1
        d2i
        ireturn
    }

    public testD2l(D)J {
        dload 1
        d2l
        lreturn
    }

    public testDadd(D, D)D {
        dload 1
        dload 3
        dadd
        dreturn
    }

    public testDconst0()D {
        dconst 0
        dreturn
    }

    public testDconst1()D {
        dconst 1
        dreturn
    }

    public testDcmpg(D, D)I {
        dload 1
        dload 3

        dcmpg

        ireturn
    }

    public testDcmpl(D, D)I {
        dload 1
        dload 3

        dcmpl

        ireturn
    }

    public <init>()V {
        aload 0
        invokespecial java/lang/Object.<init>()V
        return
    }
}